MANIFEST.in
README.rst
setup.py
collective/__init__.py
collective.configviews.egg-info/PKG-INFO
collective.configviews.egg-info/SOURCES.txt
collective.configviews.egg-info/dependency_links.txt
collective.configviews.egg-info/entry_points.txt
collective.configviews.egg-info/namespace_packages.txt
collective.configviews.egg-info/not-zip-safe
collective.configviews.egg-info/requires.txt
collective.configviews.egg-info/top_level.txt
collective/configviews/__init__.py
collective/configviews/configure.zcml
collective/configviews/events.py
collective/configviews/interfaces.py
collective/configviews/mutator.py
collective/configviews/provider.py
collective/configviews/browser/__init__.py
collective/configviews/browser/configurable_view.py
collective/configviews/browser/configure.zcml
collective/configviews/browser/form.py
collective/configviews/browser/viewlet.py
collective/configviews/locales/collective.configviews.pot
collective/configviews/locales/update.sh
collective/configviews/locales/it/LC_MESSAGES/collective.configviews.mo
collective/configviews/locales/it/LC_MESSAGES/collective.configviews.po
collective/configviews/locales/nl/LC_MESSAGES/README.txt
collective/configviews/profiles/default/actions.xml
collective/configviews/profiles/default/browserlayer.xml
collective/configviews/profiles/default/metadata.xml
collective/configviews/profiles/uninstall/actions.xml
collective/configviews/profiles/uninstall/browserlayer.xml
collective/configviews/tests/__init__.py
collective/configviews/tests/base.py
collective/configviews/tests/fake.py
collective/configviews/tests/layer.py
collective/configviews/tests/test_mutator_zopeannotation.py
collective/configviews/tests/test_provider.py
collective/configviews/tests/test_provider_interfacedefault.py
collective/configviews/tests/test_provider_ploneappregistry.py
collective/configviews/tests/test_provider_zopeannotation.py
collective/configviews/tests/example/__init__.py
collective/configviews/tests/example/browser.py
collective/configviews/tests/example/configure.zcml
collective/configviews/tests/example/example.pt
docs/HISTORY.rst
docs/INSTALL.txt
docs/LICENSE.GPL
docs/LICENSE.txt